Workbook
Name Customer_ID: Customers_data[Customer ID]
Name hsncode: Products_data[[HSN Code ]]

Sheet Sheet1
A2: Count of Name | C2: Total Customers | E2: Row Labels | F2: Sum of S Units | H2: Row Labels | I2: Sum of Amount
A3: 10 | C3: =A3 -> 10 | E3: Camera | F3: 64 | H3: Naina | I3: 3648000
E4: RGB Keyboard | F4: 50 | H4: Priya | I4: 673000
A5: Count of Product Name | C5: Total Products | E5: Headphones | F5: 45 | H5: Sunaiana | I5: 455000
A6: 10 | C6: =A6 -> 10 | E6: Wireless Printer | F6: 39 | H6: Nimit | I6: 342600
E7: Desktop | F7: 35 | H7: Nidhi | I7: 277000
A8: Sum of Amount | C8: Total Purchase Amount | E8: Smart Watch | F8: 35 | H8: Grand Total | I8: 5395600
A9: 8159740 | C9: =A9 -> 8159740 | E9: Grand Total | F9: 268
A12: Sum of Amount | C12: Total Sales Amount
A13: 5632600 | C13: =A13 -> 5632600
A16: Sum of Stock Amount | C16: Total Stock Amount
A17: 2931440 | C17: =A17 -> 2931440
C19: Profit/Loss
C20: =C17+C13-C9 -> 404300
A25: Row Labels | B25: Sum of Stock
A26: Desktop | B26: 54
A27: Headphones | B27: 53
A28: Smart Watch | B28: 48
A29: Speakers | B29: 35
A30: Laptop | B30: 35
A31: Tablets | B31: 13
A32: Wireless Printer | B32: 6
A33: Mouse | B33: 6
A34: Camera | B34: 3
A35: RGB Keyboard | B35: 0
A36: Grand Total | B36: 253

Sheet Dashboard
M10: NOTIFICATION !
M12: {=_xlfn._xlws.FILTER(Table6[[Notification ]],Table6[[Notification ]]<>"")} -> 📞 RGB Keyboard Needs to re-order ! PH: 9876540321
M13: 📞 Camera Needs to re-order ! PH: 9876540321

Sheet Customers
D6: Customer ID | E6: Name | F6: E-Mail | G6: Address
D7: 101 | E7: Rakesh | F7: rakesh67@gmail.com | G7: Delhi
D8: 102 | E8: Suresh | F8: suresh87@gmail.com | G8: Chennai
D9: 103 | E9: Nimit | F9: nimit007@gmail.com | G9: Pune
D10: 104 | E10: Naina | F10: naina67@gmail.com | G10: Rajkot
D11: 105 | E11: Sneha | F11: sneha67@gmail.com | G11: Dehradun
D12: 106 | E12: Sunaiana | F12: sunaiana67@gmail.com | G12: Meerat
D13: 107 | E13: Priya | F13: priya67@gmail.com | G13: Manali
D14: 108 | E14: Nidhi | F14: nidhi00756@gmail.com | G14: Chandigarh
D15: 109 | E15: Drishti | F15: drishti@gmail.com | G15: Kolkata
D16: 110 | E16: Rudhav | F16: rudhav@gmail.com | G16: Delhi

Sheet Products
D6: HSN Code | E6: Product Name | F6: Cost | G6: Selling Price
D7: N1001 | E7: Smart Watch | F7: 980 | G7: 1200
D8: N1002 | E8: Laptop | F8: 34500 | G8: 40000
D9: N1003 | E9: Wireless Printer | F9: 5000 | G9: 7000
D10: N1004 | E10: Desktop | F10: 20000 | G10: 22000
D11: N1005 | E11: Mouse | F11: 500 | G11: 700
D12: N1006 | E12: RGB Keyboard | F12: 2500 | G12: 3000
D13: N1007 | E13: Camera | F13: 55000 | G13: 57000
D14: N1008 | E14: Headphones | F14: 800 | G14: 1000
D15: N1009 | E15: Speakers | F15: 900 | G15: 1500
D16: N1010 | E16: Tablets | F16: 25000 | G16: 27000

Sheet Vendors
D6: HSN Code | E6: Product Name | F6: Vendor Name | G6: Phone | H6: Address
D7: N1001 | E7: Smart Watch | F7: Tech99 | G7: 9988657496 | H7: Faridabad
D8: N1002 | E8: Laptop | F8: Tech99 | G8: 9988657496 | H8: Faridabad
D9: N1003 | E9: Wireless Printer | F9: Tech99 | G9: 9988657496 | H9: Faridabad
D10: N1004 | E10: Desktop | F10: GG Traders | G10: 9876540321 | H10: Gurgaon
D11: N1005 | E11: Mouse | F11: GG Traders | G11: 9876540321 | H11: Gurgaon
D12: N1006 | E12: RGB Keyboard | F12: GG Traders | G12: 9876540321 | H12: Gurgaon
D13: N1007 | E13: Camera | F13: GG Traders | G13: 9876540321 | H13: Gurgaon
D14: N1008 | E14: Headphones | F14: Compac | G14: 9845677345 | H14: New Delhi
D15: N1009 | E15: Speakers | F15: Compac | G15: 9845677345 | H15: New Delhi
D16: N1010 | E16: Tablets | F16: Compac | G16: 9845677345 | H16: New Delhi

Sheet New Entry
E7: Purchase Entry
E9: Sale Entry

Sheet Purchase
D6: HSN Code | E6: Product Name | F6: Vendor | G6: Date | H6: Units | I6: Cost | J6: Amount
D7: N1001 | E7: =IFERROR(VLOOKUP(Purchase_data[[#This Row],[HSN Code]],Products_data[#All],2,0),"") -> Smart Watch | F7: =IFERROR(VLOOKUP(Purchase_data[[#This Row],[HSN Code]],Vendors_data[#All],3,0),"") -> Tech99 | H7: 1 | I7: =IFERROR(VLOOKUP(Purchase_data[[#This Row],[HSN Code]],Products_data[#All],3,0),"") -> 980 | J7: =IFERROR(Purchase_data[[#This Row],[Units]]*Purchase_data[[#This Row],[Cost]],"") -> 980
D8: N1004 | E8: =IFERROR(VLOOKUP(Purchase_data[[#This Row],[HSN Code]],Products_data[#All],2,0),"") -> Desktop | F8: =IFERROR(VLOOKUP(Purchase_data[[#This Row],[HSN Code]],Vendors_data[#All],3,0),"") -> GG Traders | H8: 89 | I8: =IFERROR(VLOOKUP(Purchase_data[[#This Row],[HSN Code]],Products_data[#All],3,0),"") -> 20000 | J8: =IFERROR(Purchase_data[[#This Row],[Units]]*Purchase_data[[#This Row],[Cost]],"") -> 1780000
D9: N1001 | E9: =IFERROR(VLOOKUP(Purchase_data[[#This Row],[HSN Code]],Products_data[#All],2,0),"") -> Smart Watch | F9: =IFERROR(VLOOKUP(Purchase_data[[#This Row],[HSN Code]],Vendors_data[#All],3,0),"") -> Tech99 | H9: 70 | I9: =IFERROR(VLOOKUP(Purchase_data[[#This Row],[HSN Code]],Products_data[#All],3,0),"") -> 980 | J9: =IFERROR(Purchase_data[[#This Row],[Units]]*Purchase_data[[#This Row],[Cost]],"") -> 68600
D10: N1006 | E10: =IFERROR(VLOOKUP(Purchase_data[[#This Row],[HSN Code]],Products_data[#All],2,0),"") -> RGB Keyboard | F10: =IFERROR(VLOOKUP(Purchase_data[[#This Row],[HSN Code]],Vendors_data[#All],3,0),"") -> GG Traders | H10: 50 | I10: =IFERROR(VLOOKUP(Purchase_data[[#This Row],[HSN Code]],Products_data[#All],3,0),"") -> 2500 | J10: =IFERROR(Purchase_data[[#This Row],[Units]]*Purchase_data[[#This Row],[Cost]],"") -> 125000
D11: N1005 | E11: =IFERROR(VLOOKUP(Purchase_data[[#This Row],[HSN Code]],Products_data[#All],2,0),"") -> Mouse | F11: =IFERROR(VLOOKUP(Purchase_data[[#This Row],[HSN Code]],Vendors_data[#All],3,0),"") -> GG Traders | H11: 34 | I11: =IFERROR(VLOOKUP(Purchase_data[[#This Row],[HSN Code]],Products_data[#All],3,0),"") -> 500 | J11: =IFERROR(Purchase_data[[#This Row],[Units]]*Purchase_data[[#This Row],[Cost]],"") -> 17000
D12: N1002 | E12: =IFERROR(VLOOKUP(Purchase_data[[#This Row],[HSN Code]],Products_data[#All],2,0),"") -> Laptop | F12: =IFERROR(VLOOKUP(Purchase_data[[#This Row],[HSN Code]],Vendors_data[#All],3,0),"") -> Tech99 | H12: 45 | I12: =IFERROR(VLOOKUP(Purchase_data[[#This Row],[HSN Code]],Products_data[#All],3,0),"") -> 34500 | J12: =IFERROR(Purchase_data[[#This Row],[Units]]*Purchase_data[[#This Row],[Cost]],"") -> 1552500
D13: N1010 | E13: =IFERROR(VLOOKUP(Purchase_data[[#This Row],[HSN Code]],Products_data[#All],2,0),"") -> Tablets | F13: =IFERROR(VLOOKUP(Purchase_data[[#This Row],[HSN Code]],Vendors_data[#All],3,0),"") -> Compac | H13: 23 | I13: =IFERROR(VLOOKUP(Purchase_data[[#This Row],[HSN Code]],Products_data[#All],3,0),"") -> 25000 | J13: =IFERROR(Purchase_data[[#This Row],[Units]]*Purchase_data[[#This Row],[Cost]],"") -> 575000
D14: N1003 | E14: =IFERROR(VLOOKUP(Purchase_data[[#This Row],[HSN Code]],Products_data[#All],2,0),"") -> Wireless Printer | F14: =IFERROR(VLOOKUP(Purchase_data[[#This Row],[HSN Code]],Vendors_data[#All],3,0),"") -> Tech99 | H14: 45 | I14: =IFERROR(VLOOKUP(Purchase_data[[#This Row],[HSN Code]],Products_data[#All],3,0),"") -> 5000 | J14: =IFERROR(Purchase_data[[#This Row],[Units]]*Purchase_data[[#This Row],[Cost]],"") -> 225000
D15: N1007 | E15: =IFERROR(VLOOKUP(Purchase_data[[#This Row],[HSN Code]],Products_data[#All],2,0),"") -> Camera | F15: =IFERROR(VLOOKUP(Purchase_data[[#This Row],[HSN Code]],Vendors_data[#All],3,0),"") -> GG Traders | H15: 67 | I15: =IFERROR(VLOOKUP(Purchase_data[[#This Row],[HSN Code]],Products_data[#All],3,0),"") -> 55000 | J15: =IFERROR(Purchase_data[[#This Row],[Units]]*Purchase_data[[#This Row],[Cost]],"") -> 3685000
D16: N1008 | E16: =IFERROR(VLOOKUP(Purchase_data[[#This Row],[HSN Code]],Products_data[#All],2,0),"") -> Headphones | F16: =IFERROR(VLOOKUP(Purchase_data[[#This Row],[HSN Code]],Vendors_data[#All],3,0),"") -> Compac | H16: 98 | I16: =IFERROR(VLOOKUP(Purchase_data[[#This Row],[HSN Code]],Products_data[#All],3,0),"") -> 800 | J16: =IFERROR(Purchase_data[[#This Row],[Units]]*Purchase_data[[#This Row],[Cost]],"") -> 78400
D17: N1001 | E17: =IFERROR(VLOOKUP(Purchase_data[[#This Row],[HSN Code]],Products_data[#All],2,0),"") -> Smart Watch | F17: =IFERROR(VLOOKUP(Purchase_data[[#This Row],[HSN Code]],Vendors_data[#All],3,0),"") -> Tech99 | H17: 12 | I17: =IFERROR(VLOOKUP(Purchase_data[[#This Row],[HSN Code]],Products_data[#All],3,0),"") -> 980 | J17: =IFERROR(Purchase_data[[#This Row],[Units]]*Purchase_data[[#This Row],[Cost]],"") -> 11760
D18: N1009 | E18: =IFERROR(VLOOKUP(Purchase_data[[#This Row],[HSN Code]],Products_data[#All],2,0),"") -> Speakers | F18: =IFERROR(VLOOKUP(Purchase_data[[#This Row],[HSN Code]],Vendors_data[#All],3,0),"") -> Compac | H18: 45 | I18: =IFERROR(VLOOKUP(Purchase_data[[#This Row],[HSN Code]],Products_data[#All],3,0),"") -> 900 | J18: =IFERROR(Purchase_data[[#This Row],[Units]]*Purchase_data[[#This Row],[Cost]],"") -> 40500

Sheet Sales
D6: Cust ID | E6: Cust Name | F6: HSN Code | G6: Product Name | H6: Date | I6: Stock | J6: Units | K6: Price | L6: Amount
D7: 107 | E7: =IFERROR(VLOOKUP(Sales!D7,Customers_data[#All],2,0),"") -> Priya | F7: N1003 | G7: =IFERROR(VLOOKUP(F7,Products_data[#All],2,0),"") -> Wireless Printer | H7: =TODAY() -> 46122 | I7: =IFERROR(VLOOKUP(Table5[[#This Row],[HSN Code ]],Table6[#All],6,0),"") -> 6 | J7: 39 | K7: =IFERROR(VLOOKUP(F7,Products_data[#All],4,0),"") -> 7000 | L7: =IFERROR(K7*J7,"") -> 273000
D8: 103 | E8: =IFERROR(VLOOKUP(Sales!D8,Customers_data[#All],2,0),"") -> Nimit | F8: N1005 | G8: =IFERROR(VLOOKUP(F8,Products_data[#All],2,0),"") -> Mouse | H8: =TODAY() -> 46122 | I8: =IFERROR(VLOOKUP(Table5[[#This Row],[HSN Code ]],Table6[#All],6,0),"") -> 6 | J8: 18 | K8: =IFERROR(VLOOKUP(F8,Products_data[#All],4,0),"") -> 700 | L8: =IFERROR(K8*J8,"") -> 12600
D9: 108 | E9: =IFERROR(VLOOKUP(Sales!D9,Customers_data[#All],2,0),"") -> Nidhi | F9: N1005 | G9: =IFERROR(VLOOKUP(F9,Products_data[#All],2,0),"") -> Mouse | H9: =TODAY() -> 46122 | I9: =IFERROR(VLOOKUP(Table5[[#This Row],[HSN Code ]],Table6[#All],6,0),"") -> 6 | J9: 10 | K9: =IFERROR(VLOOKUP(F9,Products_data[#All],4,0),"") -> 700 | L9: =IFERROR(K9*J9,"") -> 7000
D10: 102 | E10: =IFERROR(VLOOKUP(Sales!D10,Customers_data[#All],2,0),"") -> Suresh | F10: N1006 | G10: =IFERROR(VLOOKUP(F10,Products_data[#All],2,0),"") -> RGB Keyboard | H10: =TODAY() -> 46122 | I10: =IFERROR(VLOOKUP(Table5[[#This Row],[HSN Code ]],Table6[#All],6,0),"") -> 0 | J10: 50 | K10: =IFERROR(VLOOKUP(F10,Products_data[#All],4,0),"") -> 3000 | L10: =IFERROR(K10*J10,"") -> 150000
D11: 104 | E11: =IFERROR(VLOOKUP(Sales!D11,Customers_data[#All],2,0),"") -> Naina | F11: N1007 | G11: =IFERROR(VLOOKUP(F11,Products_data[#All],2,0),"") -> Camera | H11: =TODAY() -> 46122 | I11: =IFERROR(VLOOKUP(Table5[[#This Row],[HSN Code ]],Table6[#All],6,0),"") -> 3 | J11: 64 | K11: =IFERROR(VLOOKUP(F11,Products_data[#All],4,0),"") -> 57000 | L11: =IFERROR(K11*J11,"") -> 3648000
D12: 105 | E12: =IFERROR(VLOOKUP(Sales!D12,Customers_data[#All],2,0),"") -> Sneha | F12: N1008 | G12: =IFERROR(VLOOKUP(F12,Products_data[#All],2,0),"") -> Headphones | H12: =TODAY() -> 46122 | I12: =IFERROR(VLOOKUP(Table5[[#This Row],[HSN Code ]],Table6[#All],6,0),"") -> 53 | J12: 45 | K12: =IFERROR(VLOOKUP(F12,Products_data[#All],4,0),"") -> 1000 | L12: =IFERROR(K12*J12,"") -> 45000
D13: 106 | E13: =IFERROR(VLOOKUP(Sales!D13,Customers_data[#All],2,0),"") -> Sunaiana | F13: N1009 | G13: =IFERROR(VLOOKUP(F13,Products_data[#All],2,0),"") -> Speakers | H13: =TODAY() -> 46122 | I13: =IFERROR(VLOOKUP(Table5[[#This Row],[HSN Code ]],Table6[#All],6,0),"") -> 35 | J13: 10 | K13: =IFERROR(VLOOKUP(F13,Products_data[#All],4,0),"") -> 1500 | L13: =IFERROR(K13*J13,"") -> 15000
D14: 107 | E14: =IFERROR(VLOOKUP(Sales!D14,Customers_data[#All],2,0),"") -> Priya | F14: N1002 | G14: =IFERROR(VLOOKUP(F14,Products_data[#All],2,0),"") -> Laptop | H14: =TODAY() -> 46122 | I14: =IFERROR(VLOOKUP(Table5[[#This Row],[HSN Code ]],Table6[#All],6,0),"") -> 35 | J14: 10 | K14: =IFERROR(VLOOKUP(F14,Products_data[#All],4,0),"") -> 40000 | L14: =IFERROR(K14*J14,"") -> 400000
D15: 101 | E15: =IFERROR(VLOOKUP(Sales!D15,Customers_data[#All],2,0),"") -> Rakesh | F15: N1001 | G15: =IFERROR(VLOOKUP(F15,Products_data[#All],2,0),"") -> Smart Watch | H15: =TODAY() -> 46122 | I15: =IFERROR(VLOOKUP(Table5[[#This Row],[HSN Code ]],Table6[#All],6,0),"") -> 48 | J15: 35 | K15: =IFERROR(VLOOKUP(F15,Products_data[#All],4,0),"") -> 1200 | L15: =IFERROR(K15*J15,"") -> 42000
D16: 108 | E16: =IFERROR(VLOOKUP(Sales!D16,Customers_data[#All],2,0),"") -> Nidhi | F16: N1010 | G16: =IFERROR(VLOOKUP(F16,Products_data[#All],2,0),"") -> Tablets | H16: =TODAY() -> 46122 | I16: =IFERROR(VLOOKUP(Table5[[#This Row],[HSN Code ]],Table6[#All],6,0),"") -> 13 | J16: 10 | K16: =IFERROR(VLOOKUP(F16,Products_data[#All],4,0),"") -> 27000 | L16: =IFERROR(K16*J16,"") -> 270000
D17: 106 | E17: =IFERROR(VLOOKUP(Sales!D17,Customers_data[#All],2,0),"") -> Sunaiana | F17: N1004 | G17: =IFERROR(VLOOKUP(F17,Products_data[#All],2,0),"") -> Desktop | H17: =TODAY() -> 46122 | I17: =IFERROR(VLOOKUP(Table5[[#This Row],[HSN Code ]],Table6[#All],6,0),"") -> 54 | J17: 20 | K17: =IFERROR(VLOOKUP(F17,Products_data[#All],4,0),"") -> 22000 | L17: =IFERROR(K17*J17,"") -> 440000
D18: 103 | E18: =IFERROR(VLOOKUP(Sales!D18,Customers_data[#All],2,0),"") -> Nimit | F18: N1004 | G18: =IFERROR(VLOOKUP(F18,Products_data[#All],2,0),"") -> Desktop | H18: =TODAY() -> 46122 | I18: =IFERROR(VLOOKUP(Table5[[#This Row],[HSN Code ]],Table6[#All],6,0),"") -> 54 | J18: 15 | K18: =IFERROR(VLOOKUP(F18,Products_data[#All],4,0),"") -> 22000 | L18: =IFERROR(K18*J18,"") -> 330000
E19: =IFERROR(VLOOKUP(Sales!D19,Customers_data[#All],2,0),"") | G19: =IFERROR(VLOOKUP(F19,Products_data[#All],2,0),"") | I19: =IFERROR(VLOOKUP(Table5[[#This Row],[HSN Code ]],Table6[#All],6,0),"") | K19: =IFERROR(VLOOKUP(F19,Products_data[#All],4,0),"") | L19: =IFERROR(K19*J19,"")
E20: =IFERROR(VLOOKUP(Sales!D20,Customers_data[#All],2,0),"") | G20: =IFERROR(VLOOKUP(F20,Products_data[#All],2,0),"") | I20: =IFERROR(VLOOKUP(Table5[[#This Row],[HSN Code ]],Table6[#All],6,0),"") | K20: =IFERROR(VLOOKUP(F20,Products_data[#All],4,0),"") | L20: =IFERROR(K20*J20,"")
E21: =IFERROR(VLOOKUP(Sales!D21,Customers_data[#All],2,0),"") | G21: =IFERROR(VLOOKUP(F21,Products_data[#All],2,0),"") | I21: =IFERROR(VLOOKUP(Table5[[#This Row],[HSN Code ]],Table6[#All],6,0),"") | K21: =IFERROR(VLOOKUP(F21,Products_data[#All],4,0),"") | L21: =IFERROR(K21*J21,"")
E22: =IFERROR(VLOOKUP(Sales!D22,Customers_data[#All],2,0),"") | G22: =IFERROR(VLOOKUP(F22,Products_data[#All],2,0),"") | I22: =IFERROR(VLOOKUP(Table5[[#This Row],[HSN Code ]],Table6[#All],6,0),"") | K22: =IFERROR(VLOOKUP(F22,Products_data[#All],4,0),"") | L22: =IFERROR(K22*J22,"")
E23: =IFERROR(VLOOKUP(Sales!D23,Customers_data[#All],2,0),"") | G23: =IFERROR(VLOOKUP(F23,Products_data[#All],2,0),"") | I23: =IFERROR(VLOOKUP(Table5[[#This Row],[HSN Code ]],Table6[#All],6,0),"") | K23: =IFERROR(VLOOKUP(F23,Products_data[#All],4,0),"") | L23: =IFERROR(K23*J23,"")
E24: =IFERROR(VLOOKUP(Sales!D24,Customers_data[#All],2,0),"") | I24: =IFERROR(VLOOKUP(Table5[[#This Row],[HSN Code ]],Table6[#All],6,0),"")

Sheet Inventory
D6: HSN Code | E6: Product Name | F6: Cost | G6: P Units | H6: S Units | I6: Stock | J6: Stock Amount | K6: Notification
D7: =IFERROR(Products_data[[#This Row],[HSN Code ]],"") -> N1001 | E7: =IFERROR(Products_data[[#This Row],[Product Name]],"") -> Smart Watch | F7: =IFERROR(Products_data[[#This Row],[Cost]],"") -> 980 | G7: =IFERROR(SUMIF(Purchase_data[Product Name],Table6[[#This Row],[Product Name]],Purchase_data[Units]),"") -> 83 | H7: =SUMIF(Table5[Product Name],Table6[[#This Row],[Product Name]],Table5[Units]) -> 35 | I7: =Table6[[#This Row],[P Units]]-Table6[[#This Row],[S Units]] -> 48 | J7: =IFERROR(Table6[[#This Row],[Cost]]*Table6[[#This Row],[Stock]],"") -> 47040 | K7: =IFERROR(IF(Table6[[#This Row],[Stock]]<5,"📞 "&Table6[ [#This Row],[Product Name] ]& " Needs to re-order ! PH: "&VLOOKUP(Table6[[#This Row],[HSN Code]],Vendors_data[#All],4,0),""),"")
D8: =IFERROR(Products_data[[#This Row],[HSN Code ]],"") -> N1002 | E8: =IFERROR(Products_data[[#This Row],[Product Name]],"") -> Laptop | F8: =IFERROR(Products_data[[#This Row],[Cost]],"") -> 34500 | G8: =IFERROR(SUMIF(Purchase_data[Product Name],Table6[[#This Row],[Product Name]],Purchase_data[Units]),"") -> 45 | H8: =SUMIF(Table5[Product Name],Table6[[#This Row],[Product Name]],Table5[Units]) -> 10 | I8: =Table6[[#This Row],[P Units]]-Table6[[#This Row],[S Units]] -> 35 | J8: =IFERROR(Table6[[#This Row],[Cost]]*Table6[[#This Row],[Stock]],"") -> 1207500 | K8: =IFERROR(IF(Table6[[#This Row],[Stock]]<5,"📞 "&Table6[ [#This Row],[Product Name] ]& " Needs to re-order ! PH: "&VLOOKUP(Table6[[#This Row],[HSN Code]],Vendors_data[#All],4,0),""),"")
D9: =IFERROR(Products_data[[#This Row],[HSN Code ]],"") -> N1003 | E9: =IFERROR(Products_data[[#This Row],[Product Name]],"") -> Wireless Printer | F9: =IFERROR(Products_data[[#This Row],[Cost]],"") -> 5000 | G9: =IFERROR(SUMIF(Purchase_data[Product Name],Table6[[#This Row],[Product Name]],Purchase_data[Units]),"") -> 45 | H9: =SUMIF(Table5[Product Name],Table6[[#This Row],[Product Name]],Table5[Units]) -> 39 | I9: =Table6[[#This Row],[P Units]]-Table6[[#This Row],[S Units]] -> 6 | J9: =IFERROR(Table6[[#This Row],[Cost]]*Table6[[#This Row],[Stock]],"") -> 30000 | K9: =IFERROR(IF(Table6[[#This Row],[Stock]]<5,"📞 "&Table6[ [#This Row],[Product Name] ]& " Needs to re-order ! PH: "&VLOOKUP(Table6[[#This Row],[HSN Code]],Vendors_data[#All],4,0),""),"")
D10: =IFERROR(Products_data[[#This Row],[HSN Code ]],"") -> N1004 | E10: =IFERROR(Products_data[[#This Row],[Product Name]],"") -> Desktop | F10: =IFERROR(Products_data[[#This Row],[Cost]],"") -> 20000 | G10: =IFERROR(SUMIF(Purchase_data[Product Name],Table6[[#This Row],[Product Name]],Purchase_data[Units]),"") -> 89 | H10: =SUMIF(Table5[Product Name],Table6[[#This Row],[Product Name]],Table5[Units]) -> 35 | I10: =Table6[[#This Row],[P Units]]-Table6[[#This Row],[S Units]] -> 54 | J10: =IFERROR(Table6[[#This Row],[Cost]]*Table6[[#This Row],[Stock]],"") -> 1080000 | K10: =IFERROR(IF(Table6[[#This Row],[Stock]]<5,"📞 "&Table6[ [#This Row],[Product Name] ]& " Needs to re-order ! PH: "&VLOOKUP(Table6[[#This Row],[HSN Code]],Vendors_data[#All],4,0),""),"")
D11: =IFERROR(Products_data[[#This Row],[HSN Code ]],"") -> N1005 | E11: =IFERROR(Products_data[[#This Row],[Product Name]],"") -> Mouse | F11: =IFERROR(Products_data[[#This Row],[Cost]],"") -> 500 | G11: =IFERROR(SUMIF(Purchase_data[Product Name],Table6[[#This Row],[Product Name]],Purchase_data[Units]),"") -> 34 | H11: =SUMIF(Table5[Product Name],Table6[[#This Row],[Product Name]],Table5[Units]) -> 28 | I11: =Table6[[#This Row],[P Units]]-Table6[[#This Row],[S Units]] -> 6 | J11: =IFERROR(Table6[[#This Row],[Cost]]*Table6[[#This Row],[Stock]],"") -> 3000 | K11: =IFERROR(IF(Table6[[#This Row],[Stock]]<5,"📞 "&Table6[ [#This Row],[Product Name] ]& " Needs to re-order ! PH: "&VLOOKUP(Table6[[#This Row],[HSN Code]],Vendors_data[#All],4,0),""),"")
D12: =IFERROR(Products_data[[#This Row],[HSN Code ]],"") -> N1006 | E12: =IFERROR(Products_data[[#This Row],[Product Name]],"") -> RGB Keyboard | F12: =IFERROR(Products_data[[#This Row],[Cost]],"") -> 2500 | G12: =IFERROR(SUMIF(Purchase_data[Product Name],Table6[[#This Row],[Product Name]],Purchase_data[Units]),"") -> 50 | H12: =SUMIF(Table5[Product Name],Table6[[#This Row],[Product Name]],Table5[Units]) -> 50 | I12: =Table6[[#This Row],[P Units]]-Table6[[#This Row],[S Units]] -> 0 | J12: =IFERROR(Table6[[#This Row],[Cost]]*Table6[[#This Row],[Stock]],"") -> 0 | K12: =IFERROR(IF(Table6[[#This Row],[Stock]]<5,"📞 "&Table6[ [#This Row],[Product Name] ]& " Needs to re-order ! PH: "&VLOOKUP(Table6[[#This Row],[HSN Code]],Vendors_data[#All],4,0),""),"") -> 📞 RGB Keyboard Needs to re-order ! PH: 9876540321
D13: =IFERROR(Products_data[[#This Row],[HSN Code ]],"") -> N1007 | E13: =IFERROR(Products_data[[#This Row],[Product Name]],"") -> Camera | F13: =IFERROR(Products_data[[#This Row],[Cost]],"") -> 55000 | G13: =IFERROR(SUMIF(Purchase_data[Product Name],Table6[[#This Row],[Product Name]],Purchase_data[Units]),"") -> 67 | H13: =SUMIF(Table5[Product Name],Table6[[#This Row],[Product Name]],Table5[Units]) -> 64 | I13: =Table6[[#This Row],[P Units]]-Table6[[#This Row],[S Units]] -> 3 | J13: =IFERROR(Table6[[#This Row],[Cost]]*Table6[[#This Row],[Stock]],"") -> 165000 | K13: =IFERROR(IF(Table6[[#This Row],[Stock]]<5,"📞 "&Table6[ [#This Row],[Product Name] ]& " Needs to re-order ! PH: "&VLOOKUP(Table6[[#This Row],[HSN Code]],Vendors_data[#All],4,0),""),"") -> 📞 Camera Needs to re-order ! PH: 9876540321
D14: =IFERROR(Products_data[[#This Row],[HSN Code ]],"") -> N1008 | E14: =IFERROR(Products_data[[#This Row],[Product Name]],"") -> Headphones | F14: =IFERROR(Products_data[[#This Row],[Cost]],"") -> 800 | G14: =IFERROR(SUMIF(Purchase_data[Product Name],Table6[[#This Row],[Product Name]],Purchase_data[Units]),"") -> 98 | H14: =SUMIF(Table5[Product Name],Table6[[#This Row],[Product Name]],Table5[Units]) -> 45 | I14: =Table6[[#This Row],[P Units]]-Table6[[#This Row],[S Units]] -> 53 | J14: =IFERROR(Table6[[#This Row],[Cost]]*Table6[[#This Row],[Stock]],"") -> 42400 | K14: =IFERROR(IF(Table6[[#This Row],[Stock]]<5,"📞 "&Table6[ [#This Row],[Product Name] ]& " Needs to re-order ! PH: "&VLOOKUP(Table6[[#This Row],[HSN Code]],Vendors_data[#All],4,0),""),"")
D15: =IFERROR(Products_data[[#This Row],[HSN Code ]],"") -> N1009 | E15: =IFERROR(Products_data[[#This Row],[Product Name]],"") -> Speakers | F15: =IFERROR(Products_data[[#This Row],[Cost]],"") -> 900 | G15: =IFERROR(SUMIF(Purchase_data[Product Name],Table6[[#This Row],[Product Name]],Purchase_data[Units]),"") -> 45 | H15: =SUMIF(Table5[Product Name],Table6[[#This Row],[Product Name]],Table5[Units]) -> 10 | I15: =Table6[[#This Row],[P Units]]-Table6[[#This Row],[S Units]] -> 35 | J15: =IFERROR(Table6[[#This Row],[Cost]]*Table6[[#This Row],[Stock]],"") -> 31500 | K15: =IFERROR(IF(Table6[[#This Row],[Stock]]<5,"📞 "&Table6[ [#This Row],[Product Name] ]& " Needs to re-order ! PH: "&VLOOKUP(Table6[[#This Row],[HSN Code]],Vendors_data[#All],4,0),""),"")
D16: =IFERROR(Products_data[[#This Row],[HSN Code ]],"") -> N1010 | E16: =IFERROR(Products_data[[#This Row],[Product Name]],"") -> Tablets | F16: =IFERROR(Products_data[[#This Row],[Cost]],"") -> 25000 | G16: =IFERROR(SUMIF(Purchase_data[Product Name],Table6[[#This Row],[Product Name]],Purchase_data[Units]),"") -> 23 | H16: =SUMIF(Table5[Product Name],Table6[[#This Row],[Product Name]],Table5[Units]) -> 10 | I16: =Table6[[#This Row],[P Units]]-Table6[[#This Row],[S Units]] -> 13 | J16: =IFERROR(Table6[[#This Row],[Cost]]*Table6[[#This Row],[Stock]],"") -> 325000 | K16: =IFERROR(IF(Table6[[#This Row],[Stock]]<5,"📞 "&Table6[ [#This Row],[Product Name] ]& " Needs to re-order ! PH: "&VLOOKUP(Table6[[#This Row],[HSN Code]],Vendors_data[#All],4,0),""),"")
D17: =IFERROR(Products_data[[#This Row],[HSN Code ]],"") | E17: =IFERROR(Products_data[[#This Row],[Product Name]],"") | F17: =IFERROR(Products_data[[#This Row],[Cost]],"") | G17: =IFERROR(SUMIF(Purchase_data[Product Name],Table6[[#This Row],[Product Name]],Purchase_data[Units]),"") -> 0 | H17: =SUMIF(Table5[Product Name],Table6[[#This Row],[Product Name]],Table5[Units]) -> 0 | I17: =Table6[[#This Row],[P Units]]-Table6[[#This Row],[S Units]] -> 0 | J17: =IFERROR(Table6[[#This Row],[Cost]]*Table6[[#This Row],[Stock]],"") | K17: =IFERROR(IF(Table6[[#This Row],[Stock]]<5,"📞 "&Table6[ [#This Row],[Product Name] ]& " Needs to re-order ! PH: "&VLOOKUP(Table6[[#This Row],[HSN Code]],Vendors_data[#All],4,0),""),"")
D18: =IFERROR(Products_data[[#This Row],[HSN Code ]],"") | E18: =IFERROR(Products_data[[#This Row],[Product Name]],"") | F18: =IFERROR(Products_data[[#This Row],[Cost]],"") | G18: =IFERROR(SUMIF(Purchase_data[Product Name],Table6[[#This Row],[Product Name]],Purchase_data[Units]),"") -> 0 | H18: =SUMIF(Table5[Product Name],Table6[[#This Row],[Product Name]],Table5[Units]) -> 0 | I18: =Table6[[#This Row],[P Units]]-Table6[[#This Row],[S Units]] -> 0 | J18: =IFERROR(Table6[[#This Row],[Cost]]*Table6[[#This Row],[Stock]],"") | K18: =IFERROR(IF(Table6[[#This Row],[Stock]]<5,"📞 "&Table6[ [#This Row],[Product Name] ]& " Needs to re-order ! PH: "&VLOOKUP(Table6[[#This Row],[HSN Code]],Vendors_data[#All],4,0),""),"")
D19: =IFERROR(Products_data[[#This Row],[HSN Code ]],"") | E19: =IFERROR(Products_data[[#This Row],[Product Name]],"") | F19: =IFERROR(Products_data[[#This Row],[Cost]],"") | G19: =IFERROR(SUMIF(Purchase_data[Product Name],Table6[[#This Row],[Product Name]],Purchase_data[Units]),"") -> 0 | H19: =SUMIF(Table5[Product Name],Table6[[#This Row],[Product Name]],Table5[Units]) -> 0 | I19: =Table6[[#This Row],[P Units]]-Table6[[#This Row],[S Units]] -> 0 | J19: =IFERROR(Table6[[#This Row],[Cost]]*Table6[[#This Row],[Stock]],"") | K19: =IFERROR(IF(Table6[[#This Row],[Stock]]<5,"📞 "&Table6[ [#This Row],[Product Name] ]& " Needs to re-order ! PH: "&VLOOKUP(Table6[[#This Row],[HSN Code]],Vendors_data[#All],4,0),""),"")

Sheet Pivots
